mim_seq/CCAanalysis.py
mim_seq/__init__.py
mim_seq/ccaPlots.R
mim_seq/coveragePlot.R
mim_seq/deseq.R
mim_seq/facet_share.R
mim_seq/getCoverage.py
mim_seq/mimseq.py
mim_seq/mmQuant.py
mim_seq/modPlot.R
mim_seq/modifications
mim_seq/splitClusters.py
mim_seq/ssAlign.py
mim_seq/tRNAmap.py
mim_seq/tRNAtools.py
mim_seq/version.py
mim_seq/data/additionalMods.txt
mim_seq/data/modomics
mim_seq/data/tRNAmatureseq.cm
mim_seq/data/ce11-tRNAs/ce11-mitotRNAs.fa
mim_seq/data/ce11-tRNAs/ce11-tRNAs-detailed.out
mim_seq/data/ce11-tRNAs/ce11-tRNAs.bed
mim_seq/data/ce11-tRNAs/ce11-tRNAs.fa
mim_seq/data/ce11-tRNAs/ce11-tRNAs_name_map.txt
mim_seq/data/dm6-tRNAs/dm6-mitotRNAs.fa
mim_seq/data/dm6-tRNAs/dm6-tRNAs.bed
mim_seq/data/dm6-tRNAs/dm6-tRNAs.fa
mim_seq/data/dm6-tRNAs/dm6-tRNAs.out
mim_seq/data/dm6_eColitK/dm6-mitotRNAs.fa
mim_seq/data/dm6_eColitK/dm6-tRNAs.bed
mim_seq/data/dm6_eColitK/dm6_eColitK-tRNAs.fa
mim_seq/data/dm6_eColitK/dm6_eschColi-tRNAs.out
mim_seq/data/eschColi_K_12_MG1655-tRNAs/eschColi_K_12_MG1655-tRNAs.bed
mim_seq/data/eschColi_K_12_MG1655-tRNAs/eschColi_K_12_MG1655-tRNAs.fa
mim_seq/data/eschColi_K_12_MG1655-tRNAs/eschColi_K_12_MG1655-tRNAs.out
mim_seq/data/eschColi_K_12_MG1655-tRNAs/eschColi_K_12_MG1655-tRNAs.ss.sort
mim_seq/data/eschColi_K_12_MG1655-tRNAs/eschColi_K_12_MG1655-tRNAs_name_map.txt
mim_seq/data/eschColi_tRNA_Lys/eschColi_K_12_MG1655-tRNAs.out
mim_seq/data/eschColi_tRNA_Lys/eschColi_modomics.fa
mim_seq/data/eschColi_tRNA_Lys/eschColi_tRNA_Lys.fa
mim_seq/data/hg19-tRNAs/hg19-mitotRNAs.fa
mim_seq/data/hg19-tRNAs/hg19-tRNAs.bed
mim_seq/data/hg19-tRNAs/hg19-tRNAs.fa
mim_seq/data/hg19-tRNAs/hg19-tRNAs.out.nohap
mim_seq/data/hg19-tRNAs/hg19-tRNAs.ss.sort
mim_seq/data/hg19_eColitK/hg19-mitotRNAs.fa
mim_seq/data/hg19_eColitK/hg19-tRNAs.bed
mim_seq/data/hg19_eColitK/hg19_eColitK.fa
mim_seq/data/hg19_eColitK/hg19_eschColi-tRNAs.out
mim_seq/data/hg19_eColitK-highConf-tRNAs/hg19-mitotRNAs.fa
mim_seq/data/hg19_eColitK-highConf-tRNAs/hg19-tRNAs.bed
mim_seq-0.2.3.dist-info/LICENSE.txt
mim_seq-0.2.3.dist-info/METADATA
mim_seq-0.2.3.dist-info/WHEEL
mim_seq-0.2.3.dist-info/entry_points.txt
mim_seq-0.2.3.dist-info/top_level.txt
mim_seq-0.2.3.dist-info/RECORD
